proofreader/__init__.py
proofreader/__main__.py
proofreader/runner.py
proofreader/config/.flake8
proofreader/config/.licenses_whitelist.txt
proofreader/config/.pylintrc
proofreader/config/__init__.py
proofreader/config/utils.py
proofreader/license_checker/__init__.py
proofreader/license_checker/package.py
proofreader/utils/__init__.py
proofreader/utils/print_table.py
proofreader-0.0.8.dist-info/DESCRIPTION.rst
proofreader-0.0.8.dist-info/METADATA
proofreader-0.0.8.dist-info/RECORD
proofreader-0.0.8.dist-info/WHEEL
proofreader-0.0.8.dist-info/entry_points.txt
proofreader-0.0.8.dist-info/metadata.json
proofreader-0.0.8.dist-info/top_level.txt
