Metadata-Version: 2.0
Name: proofreader
Version: 0.0.8
Summary: Utility for running both Pylint & Flake8 on targets whilst providing global, though overridable, defaults.
Home-page: https://github.com/elifesciences/proofreader-python.git
Author: eLife Sciences Publications Ltd.
Author-email: tech-team@elifesciences.org
License: MIT
Platform: UNKNOWN
Classifier: Development Status :: 3 - Alpha
Classifier: Intended Audience :: Developers
Classifier: License :: OSI Approved :: MIT License
Classifier: Programming Language :: Python :: 2.7
Classifier: Programming Language :: Python :: 3.5
Requires-Dist: flake8 (==3.5.0)
Requires-Dist: pylint (==1.8.2)
